asterikword/__init__.py
AsterikWord-0.1.dist-info/LICENSE.txt
AsterikWord-0.1.dist-info/METADATA
AsterikWord-0.1.dist-info/WHEEL
AsterikWord-0.1.dist-info/top_level.txt
AsterikWord-0.1.dist-info/RECORD
