Metadata-Version: 2.1
Name: AsterikWord
Version: 0.1
Summary: This Program helps you to convert a given word to fancy output of asteriks 
Author: Mohammed Aqueel Ahmed
Author-email: aqueel.cbit@gmail.com
Classifier: Programming Language :: Python :: 3
Classifier: License :: OSI Approved :: MIT License
Classifier: Operating System :: OS Independent
License-File: LICENSE.txt
